queued_search/__init__.py
queued_search/indexes.py
queued_search/models.py
queued_search/signals.py
queued_search/utils.py
queued_search/management/__init__.py
queued_search/management/commands/__init__.py
queued_search/management/commands/process_search_queue.py
queued_search-2.1.0.dist-info/DESCRIPTION.rst
queued_search-2.1.0.dist-info/METADATA
queued_search-2.1.0.dist-info/pydist.json
queued_search-2.1.0.dist-info/RECORD
queued_search-2.1.0.dist-info/top_level.txt
queued_search-2.1.0.dist-info/WHEEL
